{"randUni501:8": {"positions": ["pa-23", "pa-109", "pa64", "pa109", "pa-64", "pa-71", "pa11"], "time_offset": -6}, "randUni732:7": {"positions": ["pa43", "pa55", "pa68", "pa27"], "time_offset": 21}, "randUni325:7": {"positions": [], "time_offset": 31}, "h3168c1:0": {"positions": ["pa-3", "pa-148", "pa-15", "pa-industrial2", "pa15"], "time_offset": 5}, "carIn750": {"positions": ["pa-144", "pa-120", "pa-148", "pa-131", "pa-123", "pa123"], "time_offset": 3}, "randUni677:5": {"positions": ["pa-3", "pa3", "pa152", "pa-industrial2", "pa27"], "time_offset": 5}, "randUni894:3": {"positions": ["pa-55", "pa55"], "time_offset": -30}, "randUni749:6": {"positions": ["pa-148", "pa-15"], "time_offset": 32}, "randUni113:5": {"positions": ["pa11", "pa-11"], "time_offset": 12}, "randUni251:5": {"positions": ["pa-144", "pa-109", "pa-23", "pa-123", "pa-71", "pa-152", "pa-55"], "time_offset": -5}, "randUni494:8": {"positions": ["pa-120", "pa-109", "pa-23", "pa-64", "pa-11", "pa11", "pa-55"], "time_offset": 20}, "randUni749:3": {"positions": ["pa-148", "pa-15"], "time_offset": -31}, "randUni897:4": {"positions": ["pa-123", "pa-120", "pa-131"], "time_offset": 29}, "randUni225:5": {"positions": ["pa31"], "time_offset": -12}, "carIn798": {"positions": ["pa-144", "pa-109", "pa-148", "pa-15", "pa-11", "pa-123", "pa-27", "pa11", "pa-55"], "time_offset": -7}, "randUni803:6": {"positions": ["pa-144", "pa-148", "pa-152", "pa-15"], "time_offset": 29}, "randUni149:4": {"positions": ["pa-64", "pa-148"], "time_offset": -25}, "randUni192:7": {"positions": ["pa-43", "pa-55"], "time_offset": 10}, "carIn473": {"positions": ["pa-23", "pa-148", "pa-15", "pa-11", "pa-71"], "time_offset": 2}, "carIn399": {"positions": ["pa-109", "pa-23", "pa-11"], "time_offset": -8}, "randUni485:6": {"positions": ["pa-109", "pa64", "pa-64", "pa-131", "pa-123"], "time_offset": -18}, "h2564c1:0": {"positions": ["pa-23", "pa-148", "pa-123", "pa-152", "pa-172"], "time_offset": -2}, "randUni358:4": {"positions": ["pa-55", "pa55"], "time_offset": 0}, "randUni200:4": {"positions": [], "time_offset": -28}, "carIn62": {"positions": ["pa-144", "pa-109", "pa164", "pa-148", "pa-15", "pa-11", "pa-123", "pa-152"], "time_offset": -7}, "carIn172": {"positions": ["pa-123", "pa-148", "pa-172"], "time_offset": 1}, "h2821c1:0": {"positions": ["pa-144", "pa-109", "pa-23", "pa-15", "pa-11", "pa-131", "pa-123", "pa11"], "time_offset": 12}, "randUni116:5": {"positions": ["pa-23", "pa-152"], "time_offset": 10}, "randUni484:8": {"positions": ["pa-64", "pa-120", "pa-23"], "time_offset": 28}, "randUni416:4": {"positions": ["pa-123", "pa-148", "pa-131"], "time_offset": 29}, "randUni649:7": {"positions": ["pa-123", "pa-109", "pa-152", "pa-148"], "time_offset": 12}, "h2142c1:0": {"positions": ["pa-190", "pa-148", "pa-172"], "time_offset": 8}, "h1277c1:0": {"positions": ["pa-23", "pa-109", "pa-11", "pa11", "pa-55"], "time_offset": 18}, "h2525c2:0": {"positions": [], "time_offset": 0}, "randUni911:6": {"positions": ["pa-123", "pa-131"], "time_offset": 13}, "randUni278:6": {"positions": ["pa-144", "pa-148", "pa-15", "pa-71", "pa-55"], "time_offset": 29}, "h424c1:0": {"positions": ["pa-148", "pa-152"], "time_offset": -1}, "randUni423:4": {"positions": ["pa-109", "pa-23", "pa-11", "pa11", "pa-55"], "time_offset": 29}, "randUni291:7": {"positions": ["pa-55", "pa55"], "time_offset": 29}, "randUni896:8": {"positions": ["pa-148", "pa-15", "pa-11", "pa-27", "pa-152", "pa-55"], "time_offset": -9}, "carIn372": {"positions": ["pa-23", "pa-64", "pa-148", "pa-15", "pa-131", "pa-11", "pa-123", "pa11"], "time_offset": 0}, "randUni216:8": {"positions": ["pa-190"], "time_offset": -11}, "h1222c1:0": {"positions": ["pa-23", "pa-120", "pa-109", "pa-11"], "time_offset": 19}, "randUni93:4": {"positions": ["pa-109", "pa-71", "pa-23", "pa-11"], "time_offset": 29}, "h3192c1:0": {"positions": ["pa-144", "pa-109", "pa-23", "pa-15", "pa-11", "pa-131", "pa-industrial2", "pa-123"], "time_offset": 0}, "randUni946:5": {"positions": ["pa-148", "pa-152"], "time_offset": 6}, "randUni479:5": {"positions": ["pa-55", "pa55"], "time_offset": 14}, "carIn996": {"positions": ["pa-109", "pa-23", "pa-11"], "time_offset": 0}, "randUni627:7": {"positions": ["pa-123", "pa-120", "pa-148", "pa-131"], "time_offset": 7}, "randUni224:5": {"positions": ["pa-23", "pa-11"], "time_offset": 21}, "h1919c1:0": {"positions": ["pa-120", "pa-109", "pa-131", "pa-123", "pa-172"], "time_offset": 19}, "randUni352:4": {"positions": ["pa-144", "pa-109", "pa-15", "pa-11", "pa-123"], "time_offset": -18}, "h3224c1:0": {"positions": ["pa-23", "pa-64", "pa-148", "pa-15", "pa-11", "pa11", "pa-55"], "time_offset": 5}, "randUni912:7": {"positions": ["pa-109", "pa-23", "pa11", "pa-11"], "time_offset": -33}, "randUni650:6": {"positions": ["pa-123", "pa-120"], "time_offset": 15}, "h2568c1:0": {"positions": ["pa-144", "pa-109", "pa-23", "pa-190", "pa-148", "pa-15", "pa-11", "pa-43", "pa-71"], "time_offset": 0}, "carIn499": {"positions": ["pa-144", "pa-109", "pa-148", "pa-15", "pa-11", "pa-152"], "time_offset": -7}, "h3447c1:0": {"positions": ["pa-144", "pa-109", "pa-23", "pa-148", "pa-15", "pa-11", "pa-123", "pa-27", "pa11", "pa-55"], "time_offset": -4}, "randUni944:8": {"positions": ["pa-55", "pa-23", "pa11", "pa-11"], "time_offset": -11}, "randUni920:6": {"positions": ["pa-71", "pa-172", "pa-15", "pa-11"], "time_offset": -33}, "h2527c1:0": {"positions": ["pa-109", "pa-23", "pa-148", "pa-15", "pa-11", "pa-131", "pa-123", "pa11", "pa-55"], "time_offset": 2}, "randUni71:5": {"positions": ["pa-23", "pa-71", "pa-109", "pa-11"], "time_offset": 13}, "randUni796:4": {"positions": ["pa-123", "pa-148", "pa-152", "pa-131"], "time_offset": -2}, "randUni719:4": {"positions": ["pa-144", "pa-148", "pa-15", "pa-11"], "time_offset": 3}, "carIn149": {"positions": ["pa-109", "pa-23", "pa-64", "pa-148", "pa-15", "pa-11", "pa-131", "pa-123", "pa11", "pa-55"], "time_offset": 0}, "randUni463:8": {"positions": ["pa-43", "pa-55", "pa-71"], "time_offset": -8}, "carIn856": {"positions": ["pa-120", "pa-23", "pa-148", "pa-131", "pa-123"], "time_offset": 0}, "randUni383:4": {"positions": ["pa-15"], "time_offset": -22}, "carIn554": {"positions": ["pa-144", "pa164", "pa-148", "pa-15", "pa-11", "pa-152"], "time_offset": -8}, "randUni324:5": {"positions": ["pa-144", "pa-148", "pa-15", "pa-11", "pa11"], "time_offset": 29}, "carIn525": {"positions": ["pa-23", "pa-64", "pa-148", "pa-15", "pa-11", "pa11", "pa-55"], "time_offset": 0}, "carIn539": {"positions": ["pa-120", "pa-23", "pa-109", "pa-15", "pa-11"], "time_offset": 1}, "h1563c1:0": {"positions": ["pa-144", "pa-23", "pa-148", "pa-15", "pa-11", "pa11", "pa-55"], "time_offset": -35}, "randUni867:7": {"positions": ["pa-71", "pa-11"], "time_offset": -25}, "randUni490:5": {"positions": [], "time_offset": 28}, "h3364c1:0": {"positions": ["pa-144", "pa-23", "pa-148", "pa-15", "pa-11", "pa-27", "pa11", "pa-55"], "time_offset": 0}, "randUni269:6": {"positions": ["pa-64"], "time_offset": -19}, "randUni715:6": {"positions": ["pa-190"], "time_offset": -36}, "randUni341:8": {"positions": ["pa-120", "pa-109", "pa-11"], "time_offset": 13}, "randUni295:8": {"positions": ["pa-23", "pa-15", "pa-11"], "time_offset": 29}, "h2066c1:0": {"positions": ["pa-144", "pa-109", "pa-15", "pa-11", "pa-123", "pa-71", "pa-152"], "time_offset": 12}, "randUni963:6": {"positions": ["pa-outside2", "pa-11"], "time_offset": -21}, "randUni920:5": {"positions": ["pa11", "pa-148", "pa-15", "pa-11"], "time_offset": -34}, "carIn468": {"positions": ["pa-148", "pa-15", "pa-11", "pa11", "pa-55"], "time_offset": 0}, "randUni695:5": {"positions": ["pa-55", "pa-120", "pa-109", "pa-11"], "time_offset": 17}, "carIn251": {"positions": ["pa-172"], "time_offset": 0}, "randUni957:6": {"positions": ["pa-109", "pa-15", "pa-11", "pa-123", "pa-71"], "time_offset": 24}, "carIn481": {"positions": ["pa-144", "pa-123", "pa-148", "pa-industrial2"], "time_offset": 1}, "randUni490:7": {"positions": ["pa-55"], "time_offset": -31}, "randUni155:6": {"positions": ["pa-109"], "time_offset": 29}, "h3373c2:0": {"positions": ["pa-144", "pa-109", "pa-23", "pa-15", "pa-11", "pa-131", "pa-123", "pa-55"], "time_offset": 0}, "h3345c1:0": {"positions": ["pa-144", "pa-120", "pa-109", "pa-23", "pa-15", "pa-11", "pa-71", "pa-27"], "time_offset": 0}, "h116c2:0": {"positions": ["pa-23", "pa-109", "pa-148", "pa-11", "pa-123", "pa-172"], "time_offset": 0}, "carIn993": {"positions": ["pa-144", "pa-23", "pa-148", "pa-15", "pa-11", "pa-31"], "time_offset": 0}, "carIn218": {"positions": ["pa-109", "pa-23", "pa-148", "pa-11", "pa-123", "pa11"], "time_offset": 0}, "carIn789": {"positions": ["pa-55", "pa55", "pa-109", "pa-11"], "time_offset": -8}, "h80c1:0": {"positions": ["pa-120", "pa-109", "pa-190", "pa-148", "pa-123"], "time_offset": 19}, "randUni845:7": {"positions": ["pa11", "pa-190", "pa-15", "pa-11"], "time_offset": -35}, "randUni180:6": {"positions": ["pa-23", "pa-109"], "time_offset": -11}, "randUni323:7": {"positions": ["pa-55", "pa-11"], "time_offset": -14}, "carIn854": {"positions": ["pa-120", "pa-23", "pa-109", "pa-15", "pa-11", "pa-123", "pa11", "pa-55"], "time_offset": 0}, "carIn688": {"positions": ["pa-144", "pa-109", "pa-148", "pa-15", "pa-11", "pa-131", "pa-123"], "time_offset": 0}, "randUni729:8": {"positions": ["pa-55", "pa-123", "pa-109", "pa-11"], "time_offset": 17}, "randUni886:6": {"positions": ["pa-120", "pa-131"], "time_offset": 7}, "carIn11": {"positions": ["pa-144", "pa-109", "pa-23", "pa-15", "pa-11", "pa-123", "pa-55"], "time_offset": 0}, "randUni965:4": {"positions": ["pa-23", "pa-109", "pa-15", "pa-11", "pa-123", "pa-55"], "time_offset": 16}, "randUni480:7": {"positions": ["pa-148"], "time_offset": -33}, "h2393c1:0": {"positions": ["pa-123", "pa-120", "pa-148", "pa-131"], "time_offset": -32}, "carIn729": {"positions": ["pa-144", "pa-109", "pa-23", "pa-15", "pa-131", "pa-11", "pa-123", "pa-55"], "time_offset": 0}, "h2280c1:0": {"positions": ["pa-23", "pa-109", "pa-15", "pa-11", "pa-71", "pa11", "pa-55"], "time_offset": -4}, "randUni674:6": {"positions": ["pa-123", "pa-120"], "time_offset": -21}, "randUni939:5": {"positions": [], "time_offset": 8}, "randUni9:7": {"positions": ["pa-23", "pa-109", "pa11", "pa-11"], "time_offset": -34}, "h3304c2:0": {"positions": ["pa-144", "pa-109", "pa-23", "pa-148", "pa-15", "pa-11", "pa-131", "pa-123", "pa-55"], "time_offset": 2}, "carIn605": {"positions": ["pa-23", "pa-190", "pa-148", "pa-15", "pa-11"], "time_offset": 1}, "randUni831:4": {"positions": ["pa-120", "pa-23", "pa-109", "pa-11", "pa-71", "pa11", "pa-55"], "time_offset": 12}, "randUni991:7": {"positions": ["pa-144", "pa55", "pa-148", "pa-15"], "time_offset": -9}, "randUni394:6": {"positions": ["pa-23", "pa-109", "pa-11", "pa-123", "pa11"], "time_offset": 29}, "randUni146:8": {"positions": ["pa-55"], "time_offset": 29}, "h434c1:0": {"positions": ["pa-23", "pa-109", "pa-11"], "time_offset": 2}, "randUni573:4": {"positions": ["pa-55"], "time_offset": 20}, "randUni650:8": {"positions": ["pa-120", "pa-109"], "time_offset": 14}, "randUni398:7": {"positions": ["pa55"], "time_offset": 29}, "randUni822:4": {"positions": ["pa-109", "pa-23", "pa-148", "pa-123", "pa-172"], "time_offset": 0}, "randUni686:8": {"positions": ["pa-109", "pa-123", "pa-23"], "time_offset": 5}, "randUni911:7": {"positions": ["pa-23", "pa-123", "pa-109", "pa-148"], "time_offset": 15}, "randUni145:4": {"positions": [], "time_offset": 12}, "h2315c1:0": {"positions": ["pa-23", "pa-109", "pa-131"], "time_offset": -35}, "randUni492:7": {"positions": [], "time_offset": 3}, "randUni476:8": {"positions": [], "time_offset": 29}, "carIn476": {"positions": ["pa-172"], "time_offset": 0}, "randUni115:8": {"positions": [], "time_offset": -34}, "randUni726:6": {"positions": ["pa-123"], "time_offset": 0}, "randUni215:5": {"positions": ["pa-120", "pa-109"], "time_offset": -35}, "randUni484:7": {"positions": ["pa-120", "pa-23"], "time_offset": -2}, "randUni68:3": {"positions": ["pa-55"], "time_offset": 29}, "carIn520": {"positions": ["pa-23", "pa-148", "pa-15", "pa-11", "pa-27", "pa-172", "pa-55"], "time_offset": 0}, "randUni249:8": {"positions": ["pa-55"], "time_offset": -33}, "randUni304:5": {"positions": ["pa-148"], "time_offset": -12}, "h1736c1:0": {"positions": ["pa-23", "pa-15", "pa-11", "pa-71", "pa-55", "pa55"], "time_offset": -36}, "carIn814": {"positions": ["pa-109", "pa-23", "pa-15", "pa-11", "pa-131", "pa-123"], "time_offset": 5}, "carIn923": {"positions": ["pa-144", "pa-123", "pa-172"], "time_offset": 0}, "randUni271:4": {"positions": ["pa-123", "pa-109", "pa11", "pa-11"], "time_offset": 0}, "randUni527:5": {"positions": ["pa-144", "pa-55", "pa-148", "pa-15"], "time_offset": 0}, "randUni885:4": {"positions": ["pa-outside2", "pa55", "pa-11"], "time_offset": 29}, "h803c1:0": {"positions": ["pa-23", "pa-120", "pa-109", "pa-11"], "time_offset": -31}, "h3246c1:0": {"positions": ["pa-109", "pa-15", "pa-11", "pa-123", "pa-55", "pa55"], "time_offset": 0}, "carIn636": {"positions": ["pa-109", "pa-31", "pa-23", "pa-11"], "time_offset": 0}, "randUni365:5": {"positions": ["pa-55", "pa-27"], "time_offset": -33}, "h608c1:0": {"positions": ["pa-31"], "time_offset": -2}, "randUni405:5": {"positions": ["pa-120", "pa-148"], "time_offset": 22}, "h1042c1:0": {"positions": ["pa-120", "pa-109", "pa-131"], "time_offset": -33}, "h3077c1:0": {"positions": ["pa-120", "pa-109", "pa-23", "pa-15", "pa-11", "pa-123", "pa-55", "pa55"], "time_offset": 0}, "randUni165:5": {"positions": ["pa-55", "pa-11"], "time_offset": 29}, "randUni112:4": {"positions": ["pa-55", "pa-27", "pa-11"], "time_offset": -34}, "randUni198:6": {"positions": ["pa-123", "pa-15"], "time_offset": -7}, "h1039c1:0": {"positions": ["pa-120", "pa-109"], "time_offset": 16}, "randUni25:7": {"positions": ["pa-55", "pa55", "pa-23", "pa-11"], "time_offset": 31}, "h3240c1:0": {"positions": ["pa-120", "pa-109", "pa-23", "pa-11", "pa-55", "pa55"], "time_offset": 3}, "randUni94:8": {"positions": ["pa-23", "pa-11", "pa11", "pa31", "pa-31"], "time_offset": 6}, "randUni206:4": {"positions": ["pa-outside2", "pa-23", "pa-11", "pa-27", "pa-55"], "time_offset": -31}, "randUni293:8": {"positions": ["pa-31", "pa-23"], "time_offset": -8}, "carIn691": {"positions": ["pa-outside2", "pa-120", "pa-109", "pa-23", "pa-11"], "time_offset": 0}, "randUni374:4": {"positions": ["pa-190"], "time_offset": 27}, "randUni530:4": {"positions": ["pa-109", "pa-23", "pa-11"], "time_offset": 29}, "h3231c1:0": {"positions": ["pa-23", "pa-109", "pa-55", "pa-15", "pa-11", "pa-123", "pa31", "pa-31"], "time_offset": 3}, "randUni450:7": {"positions": ["pa-144", "pa-123", "pa-172"], "time_offset": -31}, "h616c1:0": {"positions": ["pa-31"], "time_offset": 0}, "carIn753": {"positions": ["pa-outside2", "pa-120", "pa-109", "pa-23", "pa-15", "pa-11", "pa55"], "time_offset": 0}, "randUni445:8": {"positions": ["pa-55", "pa55", "pa-109", "pa-11"], "time_offset": 2}, "h2865c1:0": {"positions": ["pa-109", "pa-23", "pa-148", "pa-15", "pa-11", "pa-172"], "time_offset": -1}, "randUni565:8": {"positions": ["pa-23", "pa-123", "pa-31", "pa-109"], "time_offset": 12}, "randUni921:6": {"positions": ["pa-172"], "time_offset": 0}, "carIn371": {"positions": ["pa-172", "pa-123", "pa-148", "pa-131"], "time_offset": 0}, "carIn718": {"positions": ["pa-148", "pa-152"], "time_offset": 1}, "h2159c1:0": {"positions": ["pa-144", "pa-148", "pa-131"], "time_offset": 1}, "randUni420:7": {"positions": ["pa-144", "pa-148", "pa-15", "pa-55", "pa55"], "time_offset": 29}, "randUni997:6": {"positions": ["pa-55", "pa-71", "pa11", "pa-11"], "time_offset": -33}, "randUni11:4": {"positions": ["pa-23", "pa11", "pa-11"], "time_offset": -16}, "randUni393:5": {"positions": [], "time_offset": -6}, "randUni845:6": {"positions": ["pa-15", "pa-190", "pa-148", "pa-11"], "time_offset": 8}, "randUni502:4": {"positions": ["pa-109", "pa-11", "pa11", "pa-55", "pa55"], "time_offset": 4}, "randUni680:8": {"positions": ["pa-148"], "time_offset": -20}, "carIn216": {"positions": ["pa-144", "pa-109", "pa-23", "pa-15", "pa-11", "pa-123", "pa11", "pa123"], "time_offset": 0}, "carIn305": {"positions": ["pa-144", "pa-109", "pa-23", "pa-148", "pa-15", "pa-11", "pa-27", "pa-55"], "time_offset": 0}, "carIn881": {"positions": ["pa-148", "pa-15", "pa-11", "pa11", "pa-172"], "time_offset": 3}, "randUni653:4": {"positions": ["pa148", "pa-190", "pa-148", "pa-15", "pa-55", "pa55"], "time_offset": 0}, "randUni614:8": {"positions": ["pa-123", "pa-148"], "time_offset": 1}, "randUni688:6": {"positions": ["pa-55", "pa55", "pa-148", "pa-15"], "time_offset": -6}, "randUni954:4": {"positions": ["pa-144", "pa-148"], "time_offset": -5}, "randUni420:5": {"positions": ["pa-144", "pa-148", "pa-15", "pa-71", "pa-27"], "time_offset": -30}, "carIn640": {"positions": ["pa-123", "pa-148", "pa-172"], "time_offset": -2}, "randUni605:7": {"positions": ["pa-55", "pa55", "pa-23", "pa-11"], "time_offset": 29}, "randUni434:7": {"positions": ["pa-148", "pa-15", "pa-11", "pa11", "pa-55"], "time_offset": -20}, "randUni884:8": {"positions": [], "time_offset": -28}, "carIn575": {"positions": ["pa-23", "pa-109", "pa11", "pa-11"], "time_offset": 3}, "randUni579:6": {"positions": ["pa-144", "pa-148", "pa-15", "pa-11", "pa-71", "pa-27"], "time_offset": -28}, "h2131c1:0": {"positions": ["pa-23", "pa-15", "pa-11", "pa-123", "pa11", "pa-55", "pa55"], "time_offset": -34}, "carIn496": {"positions": ["pa-148", "pa-131"], "time_offset": 0}, "h1634c1:0": {"positions": ["pa-120", "pa-148", "pa-131"], "time_offset": -35}, "carIn774": {"positions": [], "time_offset": 1}, "h438c1:0": {"positions": ["pa-120", "pa-23", "pa-109", "pa-15", "pa-11", "pa-123", "pa11"], "time_offset": 1}, "randUni960:4": {"positions": ["pa-23", "pa-11", "pa-71", "pa-27", "pa-31"], "time_offset": -7}, "h2040c1:0": {"positions": ["pa-144", "pa-123", "pa-148", "pa-172"], "time_offset": 0}, "randUni232:7": {"positions": ["pa-43", "pa-55", "pa55", "pa-27"], "time_offset": 27}, "randUni965:5": {"positions": ["pa-109", "pa-15", "pa-11", "pa-27", "pa-55"], "time_offset": -35}, "randUni309:6": {"positions": ["pa-148", "pa-15", "pa-11", "pa11", "pa-55", "pa55"], "time_offset": -4}, "randUni30:6": {"positions": ["pa-120", "pa-109"], "time_offset": -18}, "carIn142": {"positions": ["pa-144", "pa-109", "pa-23", "pa-15", "pa-11", "pa-71", "pa-27", "pa55"], "time_offset": 0}, "randUni886:4": {"positions": ["pa-123", "pa-148"], "time_offset": -34}, "randUni494:6": {"positions": ["pa-120", "pa-109", "pa-23", "pa-11", "pa11", "pa-55", "pa55"], "time_offset": -10}, "randUni820:8": {"positions": ["pa-55", "pa-31", "pa-27", "pa-11"], "time_offset": 27}, "h3264c1:0": {"positions": ["pa-109", "pa-15", "pa-11", "pa-123", "pa-55"], "time_offset": 0}, "randUni30:4": {"positions": ["pa-120", "pa-109"], "time_offset": -18}, "randUni434:4": {"positions": ["pa-144", "pa-15", "pa-11", "pa-71", "pa-27"], "time_offset": 29}, "h3241c2:0": {"positions": ["pa-23", "pa-15", "pa-11", "pa-123", "pa11", "pa-55", "pa-31", "pa55"], "time_offset": 2}, "randUni50:6": {"positions": ["pa-55", "pa55", "pa-27"], "time_offset": 1}, "randUni142:6": {"positions": ["pa-144", "pa-148", "pa-15", "pa-11", "pa-27", "pa-55"], "time_offset": 29}, "carIn957": {"positions": ["pa-23", "pa-109", "pa-148", "pa-15", "pa-11"], "time_offset": -7}, "randUni224:6": {"positions": ["pa-23", "pa-11"], "time_offset": 18}, "randUni501:5": {"positions": ["pa-120", "pa-23", "pa-109", "pa-11", "pa-71", "pa-27", "pa55"], "time_offset": 29}, "h1010c1:0": {"positions": ["pa-123", "pa-120", "pa-148", "pa-131"], "time_offset": -33}, "carIn94": {"positions": ["pa-109", "pa-148", "pa-131"], "time_offset": 1}, "carIn7": {"positions": ["pa-23", "pa-109", "pa-11", "pa31", "pa-31"], "time_offset": 5}, "randUni52:6": {"positions": ["pa-123", "pa-148"], "time_offset": -17}, "h3282c1:0": {"positions": ["pa-120", "pa-23", "pa-109", "pa-11", "pa-43", "pa-123", "pa-55", "pa55"], "time_offset": 0}, "randUni2:4": {"positions": ["pa-190"], "time_offset": 29}, "randUni149:5": {"positions": ["pa-31", "pa-148"], "time_offset": -21}, "randUni454:7": {"positions": ["pa-148"], "time_offset": 29}, "randUni327:7": {"positions": ["pa-23", "pa-109", "pa-55", "pa-11", "pa-27", "pa31", "pa-31"], "time_offset": -7}, "randUni419:8": {"positions": ["pa-148", "pa-15", "pa-11", "pa11", "pa-55", "pa55"], "time_offset": 0}, "randUni364:8": {"positions": ["pa-23", "pa-109", "pa-11", "pa-55", "pa55"], "time_offset": 29}, "carIn20": {"positions": [], "time_offset": -7}, "randUni423:8": {"positions": ["pa-23", "pa-11", "pa11", "pa-55", "pa-31"], "time_offset": -13}, "h2522c1:0": {"positions": ["pa-148", "pa-131"], "time_offset": 5}, "h3249c2:0": {"positions": ["pa-109", "pa-15", "pa-11", "pa-27", "pa-55", "pa55"], "time_offset": 0}, "h1146c1:0": {"positions": ["pa-120", "pa-109", "pa-23", "pa-11", "pa11", "pa-55", "pa55"], "time_offset": 19}, "h1429c1:0": {"positions": ["pa-23", "pa-123", "pa-109", "pa-131"], "time_offset": 0}, "h2889c1:0": {"positions": ["pa-144", "pa-109", "pa-15", "pa-11", "pa11"], "time_offset": 21}, "randUni206:8": {"positions": ["pa-23", "pa-11", "pa11", "pa-55", "pa-31"], "time_offset": -33}, "randUni743:5": {"positions": ["pa-148"], "time_offset": 29}, "randUni659:8": {"positions": ["pa-55", "pa55"], "time_offset": 11}, "randUni869:6": {"positions": ["pa-23", "pa-11", "pa11", "pa-55", "pa55"], "time_offset": 29}, "h2456c1:0": {"positions": ["pa-144", "pa-109", "pa-23", "pa-11", "pa-131", "pa-123", "pa11", "pa123"], "time_offset": 0}, "randUni25:5": {"positions": ["pa-23", "pa-55", "pa-11", "pa11", "pa31"], "time_offset": 0}, "carIn872": {"positions": ["pa-23", "pa-148", "pa-11", "pa-123", "pa11", "pa-31"], "time_offset": -5}, "carIn836": {"positions": ["pa-23", "pa11", "pa-11"], "time_offset": 1}, "randUni362:5": {"positions": ["pa-172"], "time_offset": -34}, "randUni379:7": {"positions": ["pa-148"], "time_offset": 4}, "randUni500:5": {"positions": ["pa-123", "pa-120", "pa-109", "pa-131"], "time_offset": 2}, "carIn516": {"positions": ["pa-120", "pa-109", "pa-23", "pa-190", "pa-123", "pa31"], "time_offset": 1}, "randUni791:6": {"positions": ["pa-123", "pa-71", "pa-15"], "time_offset": -33}, "h446c1:0": {"positions": ["pa-120", "pa-148"], "time_offset": 0}, "carIn418": {"positions": ["pa-109", "pa-15", "pa-11", "pa-123", "pa11"], "time_offset": -6}, "h3267c2:0": {"positions": ["pa-109", "pa-23", "pa-148", "pa-15", "pa-11", "pa11", "pa-55", "pa55"], "time_offset": 0}, "randUni528:4": {"positions": [], "time_offset": 29}, "carIn666": {"positions": ["pa-144", "pa-109", "pa-15", "pa-11", "pa-123", "pa11"], "time_offset": 0}, "h2816c1:0": {"positions": ["pa-109", "pa-23", "pa-148", "pa-15", "pa-11", "pa11", "pa-172", "pa-31"], "time_offset": 3}}